aitoolkit_esp32/__init__.py
aitoolkit_esp32/arduino.py
aitoolkit_esp32/config.py
aitoolkit_esp32/constants.py
aitoolkit_esp32/device_detector.py
aitoolkit_esp32/firmware_flasher.py
aitoolkit_esp32/firmware_manager.py
aitoolkit_esp32/protocol.py
aitoolkit_esp32/serial_comm.py
aitoolkit_esp32-1.0.0.dist-info/licenses/LICENSE
aitoolkit_esp32-1.0.0.dist-info/METADATA
aitoolkit_esp32-1.0.0.dist-info/WHEEL
aitoolkit_esp32-1.0.0.dist-info/top_level.txt
aitoolkit_esp32-1.0.0.dist-info/RECORD
