Metadata-Version: 2.4
Name: aitoolkit-esp32
Version: 1.0.0
Summary: Arduino风格的ESP32控制库 - 通过串口控制ESP32，提供完整的Arduino API
Home-page: https://github.com/dianx12/aitoolkit-esp32
Author: Haitao Wang
Author-email: Haitao Wang <dianx12@163.com>
License: MIT License
Project-URL: Homepage, https://github.com/dianx12/aitoolkit-esp32
Project-URL: Documentation, https://github.com/dianx12/aitoolkit-esp32/blob/main/README.md
Project-URL: Repository, https://github.com/dianx12/aitoolkit-esp32
Project-URL: Bug Reports, https://github.com/dianx12/aitoolkit-esp32/issues
Keywords: esp32,arduino,serial,embedded,iot,gpio,hardware
Classifier: Development Status :: 4 - Beta
Classifier: Intended Audience :: Developers
Classifier: Intended Audience :: Education
Classifier: License :: OSI Approved :: MIT License
Classifier: Programming Language :: Python :: 3
Classifier: Programming Language :: Python :: 3.8
Classifier: Programming Language :: Python :: 3.9
Classifier: Programming Language :: Python :: 3.10
Classifier: Programming Language :: Python :: 3.11
Classifier: Programming Language :: Python :: 3.12
Classifier: Topic :: Software Development :: Embedded Systems
Classifier: Topic :: System :: Hardware
Classifier: Topic :: Education
Requires-Python: >=3.8
License-File: LICENSE
Requires-Dist: pyserial>=3.5
Requires-Dist: esptool>=4.0
Provides-Extra: dev
Requires-Dist: pytest>=6.0; extra == "dev"
Requires-Dist: pytest-cov>=2.0; extra == "dev"
Requires-Dist: black>=21.0; extra == "dev"
Requires-Dist: flake8>=3.8; extra == "dev"
Provides-Extra: web
Requires-Dist: fastapi>=0.68.0; extra == "web"
Requires-Dist: uvicorn>=0.15.0; extra == "web"
Requires-Dist: websockets>=10.0; extra == "web"
Requires-Dist: pydantic>=2.0; extra == "web"
Provides-Extra: jupyter
Requires-Dist: jupyter>=1.0.0; extra == "jupyter"
Requires-Dist: ipython>=7.0.0; extra == "jupyter"
Dynamic: author
Dynamic: home-page
Dynamic: license-file
Dynamic: requires-python
